{
    "FIS Resource client": 2.9798944993812573e-06,
    "FIS Resource initialize": 2.9798944993812573e-06,
    "FIS Errors ValidationException message": 2.9798944993812573e-06,
    "FIS Errors ValidationException initialize": 2.9798944993812573e-06,
    "FIS Errors ServiceQuotaExceededException message": 2.9798944993812573e-06,
    "FIS Errors ServiceQuotaExceededException initialize": 2.9798944993812573e-06,
    "FIS Errors ResourceNotFoundException message": 2.9798944993812573e-06,
    "FIS Errors ResourceNotFoundException initialize": 2.9798944993812573e-06,
    "FIS Errors ConflictException message": 2.9798944993812573e-06,
    "FIS Errors ConflictException initialize": 2.9798944993812573e-06,
    "FIS Client errors_module": 2.9798944993812573e-06,
    "FIS Client waiter_name": 2.9798944993812573e-06,
    "FIS Client build_request": 2.9798944993812573e-06,
    "FIS Client update_experiment_template": 2.9798944993812573e-06,
    "FIS Client untag_resource": 2.9798944993812573e-06,
    "FIS Client tag_resource": 2.9798944993812573e-06,
    "FIS Client stop_experiment": 2.9798944993812573e-06,
    "FIS Client start_experiment": 2.9798944993812573e-06,
    "FIS Client list_tags_for_resource": 2.9798944993812573e-06,
    "FIS Client list_experiment": 2.9798944993812573e-06,
    "FIS Client list_experiment_template": 2.9798944993812573e-06,
    "FIS Client list_action": 2.9798944993812573e-06,
    "FIS Client get_experiment_template": 2.9798944993812573e-06,
    "FIS Client get_experiment": 2.9798944993812573e-06,
    "FIS Client get_action": 2.9798944993812573e-06,
    "FIS Client delete_experiment_template": 2.9798944993812573e-06,
    "FIS Client create_experiment_template": 2.9798944993812573e-06,
    "FIS Client initialize": 2.9798944993812573e-06,
    "FIS Client list_target_resource_type": 2.9798944993812573e-06,
    "FIS Client get_target_resource_type": 2.9798944993812573e-06,
    "FIS Plugins Endpoints add_handler": 2.9798944993812573e-06,
    "FIS Plugins Endpoints Handler parameters_for_operation": 2.9798944993812573e-06,
    "FIS Plugins Endpoints Handler apply_endpoint_header": 2.9798944993812573e-06,
    "FIS Plugins Endpoints Handler call": 2.9798944993812573e-06,
    "FIS Endpoints UpdateExperimentTemplate buil": 2.9798944993812573e-06,
    "FIS Endpoints UntagResource buil": 2.9798944993812573e-06,
    "FIS Endpoints TagResource buil": 2.9798944993812573e-06,
    "FIS Endpoints StopExperiment buil": 2.9798944993812573e-06,
    "FIS Endpoints StartExperiment buil": 2.9798944993812573e-06,
    "FIS Endpoints ListTargetResourceTypes buil": 2.9798944993812573e-06,
    "FIS Endpoints ListTagsForResource buil": 2.9798944993812573e-06,
    "FIS Endpoints ListExperiments buil": 2.9798944993812573e-06,
    "FIS Endpoints ListExperimentTemplates buil": 2.9798944993812573e-06,
    "FIS Endpoints ListActions buil": 2.9798944993812573e-06,
    "FIS Endpoints GetTargetResourceType buil": 2.9798944993812573e-06,
    "FIS Endpoints GetExperimentTemplate buil": 2.9798944993812573e-06,
    "FIS Endpoints GetExperiment buil": 2.9798944993812573e-06,
    "FIS Endpoints GetAction buil": 2.9798944993812573e-06,
    "FIS Endpoints DeleteExperimentTemplate buil": 2.9798944993812573e-06,
    "FIS Endpoints CreateExperimentTemplate buil": 2.9798944993812573e-06,
    "FIS EndpointProvider resolve_endpoint": 2.9798944993812573e-06,
    "FIS EndpointProvider initialize": 2.9798944993812573e-06,
    "FIS initialize": 2.9798944993812573e-06,
    "FIS Endpoints UpdateTargetAccountConfiguration buil": 2.9798944993812573e-06,
    "FIS Endpoints ListTargetAccountConfigurations buil": 2.9798944993812573e-06,
    "FIS Endpoints ListExperimentTargetAccountConfigurations buil": 2.9798944993812573e-06,
    "FIS Endpoints ListExperimentResolvedTargets buil": 2.9798944993812573e-06,
    "FIS Endpoints GetTargetAccountConfiguration buil": 2.9798944993812573e-06,
    "FIS Endpoints GetExperimentTargetAccountConfiguration buil": 2.9798944993812573e-06,
    "FIS Endpoints DeleteTargetAccountConfiguration buil": 2.9798944993812573e-06,
    "FIS Endpoints CreateTargetAccountConfiguration buil": 2.9798944993812573e-06,
    "FIS Client update_target_account_configuration": 2.9798944993812573e-06,
    "FIS Client list_target_account_configuration": 2.9798944993812573e-06,
    "FIS Client list_experiment_target_account_configuration": 2.9798944993812573e-06,
    "FIS Client list_experiment_resolved_target": 2.9798944993812573e-06,
    "FIS Client get_target_account_configuration": 2.9798944993812573e-06,
    "FIS Client get_experiment_target_account_configuration": 2.9798944993812573e-06,
    "FIS Client delete_target_account_configuration": 2.9798944993812573e-06,
    "FIS Client create_target_account_configuration": 2.9798944993812573e-06
}