{
    "Keyspaces Resource client": 2.9798944993812573e-06,
    "Keyspaces Resource initializ": 2.9798944993812573e-06,
    "Keyspaces Errors ValidationException messag": 2.9798944993812573e-06,
    "Keyspaces Errors ValidationException initializ": 2.9798944993812573e-06,
    "Keyspaces Errors ServiceQuotaExceededException messag": 2.9798944993812573e-06,
    "Keyspaces Errors ServiceQuotaExceededException initializ": 2.9798944993812573e-06,
    "Keyspaces Errors ResourceNotFoundException resource_arn": 2.9798944993812573e-06,
    "Keyspaces Errors ResourceNotFoundException messag": 2.9798944993812573e-06,
    "Keyspaces Errors ResourceNotFoundException initializ": 2.9798944993812573e-06,
    "Keyspaces Errors InternalServerException messag": 2.9798944993812573e-06,
    "Keyspaces Errors InternalServerException initializ": 2.9798944993812573e-06,
    "Keyspaces Errors ConflictException messag": 2.9798944993812573e-06,
    "Keyspaces Errors ConflictException initializ": 2.9798944993812573e-06,
    "Keyspaces Errors AccessDeniedException messag": 2.9798944993812573e-06,
    "Keyspaces Errors AccessDeniedException initializ": 2.9798944993812573e-06,
    "Keyspaces Client errors_modul": 2.9798944993812573e-06,
    "Keyspaces Client waiter_nam": 2.9798944993812573e-06,
    "Keyspaces Client build_request": 2.9798944993812573e-06,
    "Keyspaces Client update_tabl": 2.9798944993812573e-06,
    "Keyspaces Client untag_resour": 2.9798944993812573e-06,
    "Keyspaces Client tag_resour": 2.9798944993812573e-06,
    "Keyspaces Client restore_tabl": 2.9798944993812573e-06,
    "Keyspaces Client list_tags_for_resour": 2.9798944993812573e-06,
    "Keyspaces Client list_tabl": 2.9798944993812573e-06,
    "Keyspaces Client list_": 2.9798944993812573e-06,
    "Keyspaces Client get_tabl": 2.9798944993812573e-06,
    "Keyspaces Client get_": 2.9798944993812573e-06,
    "Keyspaces Client delete_tabl": 2.9798944993812573e-06,
    "Keyspaces Client delete_": 2.9798944993812573e-06,
    "Keyspaces Client create_tabl": 2.9798944993812573e-06,
    "Keyspaces Client create_": 2.9798944993812573e-06,
    "Keyspaces Client initializ": 2.9798944993812573e-06,
    "Keyspaces Plugins Endpoints add_handler": 2.9798944993812573e-06,
    "Keyspaces Plugins Endpoints Handler parameters_for_operation": 2.9798944993812573e-06,
    "Keyspaces Plugins Endpoints Handler apply_endpoint_header": 2.9798944993812573e-06,
    "Keyspaces Plugins Endpoints Handler call": 2.9798944993812573e-06,
    "Keyspaces Endpoints UpdateTable buil": 2.9798944993812573e-06,
    "Keyspaces Endpoints UntagResource buil": 2.9798944993812573e-06,
    "Keyspaces Endpoints TagResource buil": 2.9798944993812573e-06,
    "Keyspaces Endpoints RestoreTable buil": 2.9798944993812573e-06,
    "Keyspaces Endpoints ListTagsForResource buil": 2.9798944993812573e-06,
    "Keyspaces Endpoints ListTables buil": 2.9798944993812573e-06,
    "Keyspaces Endpoints ListKeyspaces buil": 2.9798944993812573e-06,
    "Keyspaces Endpoints GetTable buil": 2.9798944993812573e-06,
    "Keyspaces Endpoints GetKeyspace buil": 2.9798944993812573e-06,
    "Keyspaces Endpoints DeleteTable buil": 2.9798944993812573e-06,
    "Keyspaces Endpoints DeleteKeyspace buil": 2.9798944993812573e-06,
    "Keyspaces Endpoints CreateTable buil": 2.9798944993812573e-06,
    "Keyspaces Endpoints CreateKeyspace buil": 2.9798944993812573e-06,
    "Keyspaces EndpointProvider resolve_endpoint": 2.9798944993812573e-06,
    "Keyspaces initializ": 2.9798944993812573e-06,
    "Keyspaces EndpointProvider initializ": 2.9798944993812573e-06
}