{
    "DirectConnect Resource cl": 2.9798944993812573e-06,
    "DirectConnect Resource initializ": 2.9798944993812573e-06,
    "DirectConnect Client errors_modul": 2.9798944993812573e-06,
    "DirectConnect Client waiter_nam": 2.9798944993812573e-06,
    "DirectConnect Client build_requ": 2.9798944993812573e-06,
    "DirectConnect Client update_lag": 2.9798944993812573e-06,
    "DirectConnect Client untag_resou": 2.9798944993812573e-06,
    "DirectConnect Client tag_resou": 2.9798944993812573e-06,
    "DirectConnect Client disassociate_connection_from_lag": 2.9798944993812573e-06,
    "DirectConnect Client describe_virtual_interf": 2.9798944993812573e-06,
    "DirectConnect Client describe_virtual_gateway": 2.9798944993812573e-06,
    "DirectConnect Client describe_tag": 2.9798944993812573e-06,
    "DirectConnect Client describe_l": 2.9798944993812573e-06,
    "DirectConnect Client describe_lag": 2.9798944993812573e-06,
    "DirectConnect Client describe_": 2.9798944993812573e-06,
    "DirectConnect Client describe_interconnect_l": 2.9798944993812573e-06,
    "DirectConnect Client describe_hosted_": 2.9798944993812573e-06,
    "DirectConnect Client describe_connections_on_": 2.9798944993812573e-06,
    "DirectConnect Client describe_connection_l": 2.9798944993812573e-06,
    "DirectConnect Client delete_virtual_interf": 2.9798944993812573e-06,
    "DirectConnect Client delete_lag": 2.9798944993812573e-06,
    "DirectConnect Client delete_": 2.9798944993812573e-06,
    "DirectConnect Client delete_bgp_p": 2.9798944993812573e-06,
    "DirectConnect Client create_public_virtual_interf": 2.9798944993812573e-06,
    "DirectConnect Client create_private_virtual_interf": 2.9798944993812573e-06,
    "DirectConnect Client create_lag": 2.9798944993812573e-06,
    "DirectConnect Client create_": 2.9798944993812573e-06,
    "DirectConnect Client create_bgp_p": 2.9798944993812573e-06,
    "DirectConnect Client confirm_public_virtual_interf": 2.9798944993812573e-06,
    "DirectConnect Client confirm_private_virtual_interf": 2.9798944993812573e-06,
    "DirectConnect Client confirm_": 2.9798944993812573e-06,
    "DirectConnect Client associate_virtual_interf": 2.9798944993812573e-06,
    "DirectConnect Client associate_hosted_": 2.9798944993812573e-06,
    "DirectConnect Client associate_connection_with_lag": 2.9798944993812573e-06,
    "DirectConnect Client allocate_public_virtual_interf": 2.9798944993812573e-06,
    "DirectConnect Client allocate_private_virtual_interf": 2.9798944993812573e-06,
    "DirectConnect Client allocate_hosted_": 2.9798944993812573e-06,
    "DirectConnect Client allocate_connection_on_": 2.9798944993812573e-06,
    "DirectConnect Client initializ": 2.9798944993812573e-06,
    "Aws DirectConnect Resource cl": 2.9798944993812573e-06,
    "Aws DirectConnect Resource initializ": 2.9798944993812573e-06,
    "Aws DirectConnect Client errors_modul": 2.9798944993812573e-06,
    "Aws DirectConnect Client waiter_nam": 2.9798944993812573e-06,
    "Aws DirectConnect Client build_requ": 2.9798944993812573e-06,
    "Aws DirectConnect Client untag_resou": 2.9798944993812573e-06,
    "Aws DirectConnect Client tag_resou": 2.9798944993812573e-06,
    "Aws DirectConnect Client describe_virtual_interf": 2.9798944993812573e-06,
    "Aws DirectConnect Client describe_virtual_gateway": 2.9798944993812573e-06,
    "Aws DirectConnect Client describe_tag": 2.9798944993812573e-06,
    "Aws DirectConnect Client describe_l": 2.9798944993812573e-06,
    "Aws DirectConnect Client describe_": 2.9798944993812573e-06,
    "Aws DirectConnect Client describe_interconnect_l": 2.9798944993812573e-06,
    "Aws DirectConnect Client describe_connections_on_": 2.9798944993812573e-06,
    "Aws DirectConnect Client describe_connection_l": 2.9798944993812573e-06,
    "Aws DirectConnect Client delete_virtual_interf": 2.9798944993812573e-06,
    "Aws DirectConnect Client delete_": 2.9798944993812573e-06,
    "Aws DirectConnect Client create_public_virtual_interf": 2.9798944993812573e-06,
    "Aws DirectConnect Client create_private_virtual_interf": 2.9798944993812573e-06,
    "Aws DirectConnect Client create_": 2.9798944993812573e-06,
    "Aws DirectConnect Client confirm_public_virtual_interf": 2.9798944993812573e-06,
    "Aws DirectConnect Client confirm_private_virtual_interf": 2.9798944993812573e-06,
    "Aws DirectConnect Client confirm_": 2.9798944993812573e-06,
    "Aws DirectConnect Client allocate_public_virtual_interf": 2.9798944993812573e-06,
    "Aws DirectConnect Client allocate_private_virtual_interf": 2.9798944993812573e-06,
    "Aws DirectConnect Client allocate_connection_on_": 2.9798944993812573e-06,
    "Aws DirectConnect Client initializ": 2.9798944993812573e-06,
    "Aws DirectConnect Client delete_bgp_p": 2.9798944993812573e-06,
    "Aws DirectConnect Client create_bgp_p": 2.9798944993812573e-06,
    "DirectConnect Client describe_direct_connect_gateway": 2.9798944993812573e-06,
    "DirectConnect Client describe_direct_connect_gateway_attachm": 2.9798944993812573e-06,
    "DirectConnect Client describe_direct_connect_gateway_": 2.9798944993812573e-06,
    "DirectConnect Client delete_direct_connect_gateway_": 2.9798944993812573e-06,
    "DirectConnect Client delete_direct_connect_gateway": 2.9798944993812573e-06,
    "DirectConnect Client create_direct_connect_gateway_": 2.9798944993812573e-06,
    "DirectConnect Client create_direct_connect_gateway": 2.9798944993812573e-06,
    "DirectConnect Client update_virtual_interface_attribu": 2.9798944993812573e-06,
    "DirectConnect Client update_direct_connect_gateway_": 2.9798944993812573e-06,
    "DirectConnect Client describe_direct_connect_gateway_association_proposal": 2.9798944993812573e-06,
    "DirectConnect Client delete_direct_connect_gateway_association_proposal": 2.9798944993812573e-06,
    "DirectConnect Client create_direct_connect_gateway_association_proposal": 2.9798944993812573e-06,
    "DirectConnect Client accept_direct_connect_gateway_association_proposal": 2.9798944993812573e-06,
    "DirectConnect Client create_transit_virtual_interf": 2.9798944993812573e-06,
    "DirectConnect Client confirm_transit_virtual_interf": 2.9798944993812573e-06,
    "DirectConnect Client allocate_transit_virtual_interf": 2.9798944993812573e-06,
    "DirectConnect Errors DirectConnectServerException messag": 2.9798944993812573e-06,
    "DirectConnect Errors DirectConnectServerException initializ": 2.9798944993812573e-06,
    "DirectConnect Errors DirectConnectClientException messag": 2.9798944993812573e-06,
    "DirectConnect Errors DirectConnectClientException initializ": 2.9798944993812573e-06,
    "DirectConnect Errors TooManyTagsException initializ": 2.9798944993812573e-06,
    "DirectConnect Errors DuplicateTagKeysException initializ": 2.9798944993812573e-06,
    "DirectConnect Client stop_bgp_failover_": 2.9798944993812573e-06,
    "DirectConnect Client start_bgp_failover_": 2.9798944993812573e-06,
    "DirectConnect Client list_virtual_interface_test_history": 2.9798944993812573e-06,
    "DirectConnect Client update_": 2.9798944993812573e-06,
    "DirectConnect Client disassociate_mac_sec_key": 2.9798944993812573e-06,
    "DirectConnect Client associate_mac_sec_key": 2.9798944993812573e-06,
    "DirectConnect Client update_direct_connect_gateway": 2.9798944993812573e-06,
    "DirectConnect Client describe_router_configu": 2.9798944993812573e-06,
    "DirectConnect Client describe_customer_m": 2.9798944993812573e-06,
    "DirectConnect Client confirm_customer_agreem": 2.9798944993812573e-06,
    "DirectConnect Plugins Endpoints add_handl": 2.9798944993812573e-06,
    "DirectConnect Plugins Endpoints Handler parameters_for_op": 2.9798944993812573e-06,
    "DirectConnect Plugins Endpoints Handler apply_endpoint_h": 2.9798944993812573e-06,
    "DirectConnect Plugins Endpoints Handler call": 2.9798944993812573e-06,
    "DirectConnect Endpoints UpdateVirtualInterfaceAttributes buil": 2.9798944993812573e-06,
    "DirectConnect Endpoints UpdateLag buil": 2.9798944993812573e-06,
    "DirectConnect Endpoints UpdateDirectConnectGatewayAssociation buil": 2.9798944993812573e-06,
    "DirectConnect Endpoints UpdateDirectConnectGateway buil": 2.9798944993812573e-06,
    "DirectConnect Endpoints UpdateConnection buil": 2.9798944993812573e-06,
    "DirectConnect Endpoints UntagResource buil": 2.9798944993812573e-06,
    "DirectConnect Endpoints TagResource buil": 2.9798944993812573e-06,
    "DirectConnect Endpoints StopBgpFailoverTest buil": 2.9798944993812573e-06,
    "DirectConnect Endpoints StartBgpFailoverTest buil": 2.9798944993812573e-06,
    "DirectConnect Endpoints ListVirtualInterfaceTestHistory buil": 2.9798944993812573e-06,
    "DirectConnect Endpoints DisassociateMacSecKey buil": 2.9798944993812573e-06,
    "DirectConnect Endpoints DisassociateConnectionFromLag buil": 2.9798944993812573e-06,
    "DirectConnect Endpoints DescribeVirtualInterfaces buil": 2.9798944993812573e-06,
    "DirectConnect Endpoints DescribeVirtualGateways buil": 2.9798944993812573e-06,
    "DirectConnect Endpoints DescribeTags buil": 2.9798944993812573e-06,
    "DirectConnect Endpoints DescribeRouterConfiguration buil": 2.9798944993812573e-06,
    "DirectConnect Endpoints DescribeLocations buil": 2.9798944993812573e-06,
    "DirectConnect Endpoints DescribeLoa buil": 2.9798944993812573e-06,
    "DirectConnect Endpoints DescribeLags buil": 2.9798944993812573e-06,
    "DirectConnect Endpoints DescribeInterconnects buil": 2.9798944993812573e-06,
    "DirectConnect Endpoints DescribeInterconnectLoa buil": 2.9798944993812573e-06,
    "DirectConnect Endpoints DescribeHostedConnections buil": 2.9798944993812573e-06,
    "DirectConnect Endpoints DescribeDirectConnectGateways buil": 2.9798944993812573e-06,
    "DirectConnect Endpoints DescribeDirectConnectGatewayAttachments buil": 2.9798944993812573e-06,
    "DirectConnect Endpoints DescribeDirectConnectGatewayAssociations buil": 2.9798944993812573e-06,
    "DirectConnect Endpoints DescribeDirectConnectGatewayAssociationProposals buil": 2.9798944993812573e-06,
    "DirectConnect Endpoints DescribeCustomerMetadata buil": 2.9798944993812573e-06,
    "DirectConnect Endpoints DescribeConnectionsOnInterconnect buil": 2.9798944993812573e-06,
    "DirectConnect Endpoints DescribeConnections buil": 2.9798944993812573e-06,
    "DirectConnect Endpoints DescribeConnectionLoa buil": 2.9798944993812573e-06,
    "DirectConnect Endpoints DeleteVirtualInterface buil": 2.9798944993812573e-06,
    "DirectConnect Endpoints DeleteLag buil": 2.9798944993812573e-06,
    "DirectConnect Endpoints DeleteInterconnect buil": 2.9798944993812573e-06,
    "DirectConnect Endpoints DeleteDirectConnectGatewayAssociationProposal buil": 2.9798944993812573e-06,
    "DirectConnect Endpoints DeleteDirectConnectGatewayAssociation buil": 2.9798944993812573e-06,
    "DirectConnect Endpoints DeleteDirectConnectGateway buil": 2.9798944993812573e-06,
    "DirectConnect Endpoints DeleteConnection buil": 2.9798944993812573e-06,
    "DirectConnect Endpoints DeleteBGPPeer buil": 2.9798944993812573e-06,
    "DirectConnect Endpoints CreateTransitVirtualInterface buil": 2.9798944993812573e-06,
    "DirectConnect Endpoints CreatePublicVirtualInterface buil": 2.9798944993812573e-06,
    "DirectConnect Endpoints CreatePrivateVirtualInterface buil": 2.9798944993812573e-06,
    "DirectConnect Endpoints CreateLag buil": 2.9798944993812573e-06,
    "DirectConnect Endpoints CreateInterconnect buil": 2.9798944993812573e-06,
    "DirectConnect Endpoints CreateDirectConnectGatewayAssociationProposal buil": 2.9798944993812573e-06,
    "DirectConnect Endpoints CreateDirectConnectGatewayAssociation buil": 2.9798944993812573e-06,
    "DirectConnect Endpoints CreateDirectConnectGateway buil": 2.9798944993812573e-06,
    "DirectConnect Endpoints CreateConnection buil": 2.9798944993812573e-06,
    "DirectConnect Endpoints CreateBGPPeer buil": 2.9798944993812573e-06,
    "DirectConnect Endpoints ConfirmTransitVirtualInterface buil": 2.9798944993812573e-06,
    "DirectConnect Endpoints ConfirmPublicVirtualInterface buil": 2.9798944993812573e-06,
    "DirectConnect Endpoints ConfirmPrivateVirtualInterface buil": 2.9798944993812573e-06,
    "DirectConnect Endpoints ConfirmCustomerAgreement buil": 2.9798944993812573e-06,
    "DirectConnect Endpoints ConfirmConnection buil": 2.9798944993812573e-06,
    "DirectConnect Endpoints AssociateVirtualInterface buil": 2.9798944993812573e-06,
    "DirectConnect Endpoints AssociateMacSecKey buil": 2.9798944993812573e-06,
    "DirectConnect Endpoints AssociateHostedConnection buil": 2.9798944993812573e-06,
    "DirectConnect Endpoints AssociateConnectionWithLag buil": 2.9798944993812573e-06,
    "DirectConnect Endpoints AllocateTransitVirtualInterface buil": 2.9798944993812573e-06,
    "DirectConnect Endpoints AllocatePublicVirtualInterface buil": 2.9798944993812573e-06,
    "DirectConnect Endpoints AllocatePrivateVirtualInterface buil": 2.9798944993812573e-06,
    "DirectConnect Endpoints AllocateHostedConnection buil": 2.9798944993812573e-06,
    "DirectConnect Endpoints AllocateConnectionOnInterconnect buil": 2.9798944993812573e-06,
    "DirectConnect Endpoints AcceptDirectConnectGatewayAssociationProposal buil": 2.9798944993812573e-06,
    "DirectConnect EndpointProvider resolve_endp": 2.9798944993812573e-06,
    "DirectConnect EndpointProvider initializ": 2.9798944993812573e-06,
    "DirectConnect initializ": 2.9798944993812573e-06
}