{
    "Coveralls should_run?": 2.9798944993812573e-06,
    "Coveralls start!": 2.9798944993812573e-06,
    "Coveralls setup!": 2.9798944993812573e-06,
    "Coveralls wear!": 2.9798944993812573e-06,
    "Coveralls SimpleCov Formatter short_filenam": 2.9798944993812573e-06,
    "Coveralls SimpleCov Formatter output_messag": 2.9798944993812573e-06,
    "Coveralls SimpleCov Formatter format": 2.9798944993812573e-06,
    "Coveralls Configuration relevant_en": 2.9798944993812573e-06,
    "Coveralls Configuration git": 2.9798944993812573e-06,
    "Coveralls Configuration rails_root": 2.9798944993812573e-06,
    "Coveralls Configuration simplecov_root": 2.9798944993812573e-06,
    "Coveralls Configuration pwd": 2.9798944993812573e-06,
    "Coveralls Configuration root": 2.9798944993812573e-06,
    "Coveralls Configuration configuration_path": 2.9798944993812573e-06,
    "Coveralls Configuration configuration": 2.9798944993812573e-06,
    "Coveralls CommandLine ensure_can_run_locally!": 2.9798944993812573e-06,
    "Coveralls CommandLine rsp": 2.9798944993812573e-06,
    "Coveralls API apified_hash": 2.9798944993812573e-06,
    "Coveralls API hash_to_fi": 2.9798944993812573e-06,
    "Coveralls API endpoint_to_u": 2.9798944993812573e-06,
    "Coveralls API post_json": 2.9798944993812573e-06,
    "Coveralls Configuration yaml_config": 2.9798944993812573e-06,
    "Coveralls CommandLine open_token_based_u": 2.9798944993812573e-06,
    "Coveralls CommandLine last": 2.9798944993812573e-06,
    "Coveralls CommandLine servi": 2.9798944993812573e-06,
    "Coveralls CommandLine open": 2.9798944993812573e-06,
    "Coveralls CommandLine report": 2.9798944993812573e-06,
    "Coveralls CommandLine push": 2.9798944993812573e-06,
    "Coveralls CommandLine version": 2.9798944993812573e-06,
    "Coveralls API disable_net_blockers!": 2.9798944993812573e-06,
    "Coveralls noisy?": 2.9798944993812573e-06,
    "Coveralls SimpleCov Formatter display_": 2.9798944993812573e-06,
    "Coveralls SimpleCov Formatter display_result": 2.9798944993812573e-06,
    "Coveralls push!": 2.9798944993812573e-06,
    "Coveralls wear_merged!": 2.9798944993812573e-06,
    "Coveralls RakeTask initializ": 2.9798944993812573e-06,
    "Coveralls NilFormatter format": 2.9798944993812573e-06,
    "Coveralls Output print": 2.9798944993812573e-06,
    "Coveralls Output put": 2.9798944993812573e-06,
    "Coveralls Output format": 2.9798944993812573e-06,
    "Coveralls will_run?": 2.9798944993812573e-06,
    "Coveralls Output silent?": 2.9798944993812573e-06,
    "Coveralls Output output": 2.9798944993812573e-06,
    "Coveralls Output no_color?": 2.9798944993812573e-06,
    "Coveralls Configuration set_service_params_for_generic_ci": 2.9798944993812573e-06,
    "Coveralls Configuration set_service_params_for_coveralls_": 2.9798944993812573e-06,
    "Coveralls Configuration set_service_params_for_jenkin": 2.9798944993812573e-06,
    "Coveralls Configuration set_service_params_for_semaph": 2.9798944993812573e-06,
    "Coveralls Configuration set_service_params_for_circleci": 2.9798944993812573e-06,
    "Coveralls Configuration set_service_params_for_travi": 2.9798944993812573e-06,
    "Coveralls Configuration set_service_params_for_tddium": 2.9798944993812573e-06,
    "Coveralls Configuration set_service_params_for_appvey": 2.9798944993812573e-06,
    "Coveralls Configuration set_standard_service_params_for_generic_ci": 2.9798944993812573e-06,
    "Coveralls SimpleCov Formatter get_source_fi": 2.9798944993812573e-06,
    "Coveralls API build_request_body": 2.9798944993812573e-06,
    "Coveralls API build_request": 2.9798944993812573e-06,
    "Coveralls API build_client": 2.9798944993812573e-06,
    "Coveralls API endpoint_to_uri": 2.9798944993812573e-06,
    "Coveralls Configuration set_service_params_for_gitlab": 2.9798944993812573e-06
}